AUTHORS
LICENSE
MANIFEST.in
NEWS
README
setup.py
src/HTSQL_MSSQL.egg-info/PKG-INFO
src/HTSQL_MSSQL.egg-info/SOURCES.txt
src/HTSQL_MSSQL.egg-info/dependency_links.txt
src/HTSQL_MSSQL.egg-info/entry_points.txt
src/HTSQL_MSSQL.egg-info/not-zip-safe
src/HTSQL_MSSQL.egg-info/requires.txt
src/HTSQL_MSSQL.egg-info/top_level.txt
src/htsql_mssql/__init__.py
src/htsql_mssql/core/__init__.py
src/htsql_mssql/core/connect.py
src/htsql_mssql/core/introspect.py
src/htsql_mssql/core/split_sql.py
src/htsql_mssql/core/tr/__init__.py
src/htsql_mssql/core/tr/compile.py
src/htsql_mssql/core/tr/dump.py
src/htsql_mssql/core/tr/encode.py
src/htsql_mssql/core/tr/reduce.py